cli.py
pychatgpt_cli-0.0.3.dist-info/LICENSE
pychatgpt_cli-0.0.3.dist-info/METADATA
pychatgpt_cli-0.0.3.dist-info/WHEEL
pychatgpt_cli-0.0.3.dist-info/entry_points.txt
pychatgpt_cli-0.0.3.dist-info/top_level.txt
pychatgpt_cli-0.0.3.dist-info/RECORD
