Metadata-Version: 2.1
Name: pychatgpt-cli
Version: 0.0.3
Summary: A command-line ChatGPT tool using official OpenAI API.
Home-page: https://github.com/callmexss/pychatgpt-cli
Author: callmexss
Author-email: callmexss@126.com
Classifier: Development Status :: 3 - Alpha
Classifier: Programming Language :: Python :: 3.9
Classifier: License :: OSI Approved :: MIT License
Classifier: Operating System :: OS Independent
License-File: LICENSE
Requires-Dist: click
Requires-Dist: openai (>=0.27.0)
Requires-Dist: rich
